MCHostResolver/MCHostResolver.py
MCHostResolver/__init__.py
MCHostResolver-1.5.dist-info/LICENSE
MCHostResolver-1.5.dist-info/METADATA
MCHostResolver-1.5.dist-info/WHEEL
MCHostResolver-1.5.dist-info/top_level.txt
MCHostResolver-1.5.dist-info/RECORD
