Metadata-Version: 2.1
Name: MCHostResolver
Version: 1.5
Summary: A module for resolving MC hostnames
Home-page: https://github.com/itskek/MCHostResolver
Author: itskekoff
Author-email: itskekoff@gmail.com
License: MIT
Platform: UNKNOWN
License-File: LICENSE
Requires-Dist: colorama
Requires-Dist: dnspython
